hisui-2026.1.0.dev0.data/scripts/hisui
hisui-2026.1.0.dev0.dist-info/METADATA
hisui-2026.1.0.dev0.dist-info/WHEEL
hisui-2026.1.0.dev0.dist-info/licenses/LICENSE
hisui/__init__.py
hisui-2026.1.0.dev0.dist-info/RECORD
