Metadata-Version: 2.4
Name: hisui
Version: 2026.1.0.dev0
Classifier: License :: OSI Approved :: Apache Software License
Classifier: Operating System :: MacOS
Classifier: Operating System :: POSIX :: Linux
Classifier: Programming Language :: Rust
Classifier: Programming Language :: Python
Classifier: Programming Language :: Python :: 3
Classifier: Programming Language :: Python :: 3.12
Classifier: Programming Language :: Python :: 3.13
Classifier: Programming Language :: Python :: 3.14
Classifier: Programming Language :: Python :: 3 :: Only
Classifier: Programming Language :: Python :: Implementation :: CPython
License-File: LICENSE
Summary: CLI package for using Recording Composition Tool Hisui from Python
Home-Page: https://github.com/shiguredo/hisui
Author-email: "Shiguredo Inc." <contact+pypi@shiguredo.jp>
License-Expression: Apache-2.0
Requires-Python: >=3.12
Project-URL: Homepage, https://github.com/shiguredo/hisui
Project-URL: Repository, https://github.com/shiguredo/hisui
